spike_prime_connect/__main__.py
spike_prime_connect/spike_prime_compyne.py
spike_prime_connect/spikeapi.py
spike_prime_connect-0.1.4.dist-info/entry_points.txt
spike_prime_connect-0.1.4.dist-info/METADATA
spike_prime_connect-0.1.4.dist-info/WHEEL
spike_prime_connect-0.1.4.dist-info/RECORD
